quickapp.cpython-310-darwin.so
quickapp.pyi
reprep_quickapp.cpython-310-darwin.so
reprep_quickapp.pyi
quickapp/py.typed
reprep_quickapp/py.typed
QuickApp_z7-7.2.dist-info/METADATA
QuickApp_z7-7.2.dist-info/WHEEL
QuickApp_z7-7.2.dist-info/entry_points.txt
QuickApp_z7-7.2.dist-info/top_level.txt
QuickApp_z7-7.2.dist-info/zip-safe
QuickApp_z7-7.2.dist-info/RECORD
